segkv/__init__.py
segkv/core.py
segkv/py.typed
segkv-0.1.0.dist-info/METADATA
segkv-0.1.0.dist-info/WHEEL
segkv-0.1.0.dist-info/licenses/LICENSE
segkv-0.1.0.dist-info/RECORD
