Metadata-Version: 2.4
Name: segkv
Version: 0.1.0
Summary: A log-structured storage engine with compaction for Python
Project-URL: Homepage, https://github.com/janettai/segkv
Project-URL: Repository, https://github.com/janettai/segkv
Project-URL: Issues, https://github.com/janettai/segkv/issues
Author: Nana Adjei Manu
License-Expression: MIT
License-File: LICENSE
Keywords: database,embedded,key-value,log-structured,lsm,storage
Classifier: Development Status :: 3 - Alpha
Classifier: Intended Audience :: Developers
Classifier: License :: OSI Approved :: MIT License
Classifier: Operating System :: OS Independent
Classifier: Programming Language :: Python :: 3
Classifier: Programming Language :: Python :: 3.10
Classifier: Programming Language :: Python :: 3.11
Classifier: Programming Language :: Python :: 3.12
Classifier: Programming Language :: Python :: 3.13
Classifier: Programming Language :: Python :: 3.14
Classifier: Topic :: Database
Classifier: Topic :: Database :: Database Engines/Servers
Classifier: Typing :: Typed
Requires-Python: >=3.10
